auv_cal/__init__.py
auv_cal/auv_cal.py
auv_cal/calibration.py
auv_cal/camera_calibrator.py
auv_cal/cone_fitting.py
auv_cal/euler_angles_from_rotation_matrix.py
auv_cal/laser_calibrator.py
auv_cal/plane_fitting.py
auv_cal/plot_points_and_planes.py
auv_cal/ransac.py
auv_cal/default_yaml/default_calibration.yaml
auv_nav/__init__.py
auv_nav/auv_nav.py
auv_nav/convert.py
auv_nav/parse.py
auv_nav/process.py
auv_nav/sensors.py
auv_nav/default_yaml/auv_nav.yaml
auv_nav/default_yaml/ae2000/YK17-23C/camera.yaml
auv_nav/default_yaml/ae2000/YK17-23C/mission.yaml
auv_nav/default_yaml/ae2000/YK17-23C/vehicle.yaml
auv_nav/default_yaml/alr/dy152/camera.yaml
auv_nav/default_yaml/alr/dy152/mission.yaml
auv_nav/default_yaml/alr/dy152/vehicle.yaml
auv_nav/default_yaml/alr/insite/camera.yaml
auv_nav/default_yaml/alr/insite/mission.yaml
auv_nav/default_yaml/alr/insite/vehicle.yaml
auv_nav/default_yaml/alr/jc220/camera.yaml
auv_nav/default_yaml/as6/DY109/camera.yaml
auv_nav/default_yaml/as6/DY109/mission.yaml
auv_nav/default_yaml/as6/DY109/vehicle.yaml
auv_nav/default_yaml/hybis/camera.yaml
auv_nav/default_yaml/hybis/mission.yaml
auv_nav/default_yaml/hybis/vehicle.yaml
auv_nav/default_yaml/ntnu_rov/mission.yaml
auv_nav/default_yaml/ntnu_rov/vehicle.yaml
auv_nav/default_yaml/ntnu_stereo/tautra21/camera.yaml
auv_nav/default_yaml/ntnu_stereo/tautra21/mission.yaml
auv_nav/default_yaml/ntnu_stereo/tautra21/vehicle.yaml
auv_nav/default_yaml/rosbag/grassmap/camera.yaml
auv_nav/default_yaml/rosbag/grassmap/mission.yaml
auv_nav/default_yaml/rosbag/grassmap/vehicle.yaml
auv_nav/default_yaml/smarty200/stereo_gopro/camera.yaml
auv_nav/default_yaml/smarty200/stereo_gopro/mission.yaml
auv_nav/default_yaml/smarty200/stereo_gopro/vehicle.yaml
auv_nav/default_yaml/smarty200/voyis/camera.yaml
auv_nav/default_yaml/smarty200/voyis/mission.yaml
auv_nav/default_yaml/smarty200/voyis/vehicle.yaml
auv_nav/default_yaml/ts1/SSK17-01/camera.yaml
auv_nav/default_yaml/ts1/SSK17-01/mission.yaml
oplab_pipeline-1.1.7.dist-info/licenses/LICENSE
oplab_pipeline-1.1.7.dist-info/METADATA
oplab_pipeline-1.1.7.dist-info/WHEEL
oplab_pipeline-1.1.7.dist-info/entry_points.txt
oplab_pipeline-1.1.7.dist-info/top_level.txt
oplab_pipeline-1.1.7.dist-info/RECORD
