Metadata-Version: 2.4
Name: oplab_pipeline
Version: 1.1.7
Summary: Toolchain for AUV dive processing, camera calibration and image correction
Home-page: https://github.com/ocean-perception/oplab_pipeline
Author: Ocean Perception - University of Southampton
Author-email: miquel.massot-campos@soton.ac.uk
License: BSD
Classifier: Development Status :: 2 - Pre-Alpha
Classifier: Intended Audience :: Developers
Classifier: Intended Audience :: Science/Research
Classifier: License :: OSI Approved :: BSD License
Classifier: Operating System :: OS Independent
Classifier: Programming Language :: Python
Classifier: Programming Language :: Python :: 3
Classifier: Programming Language :: Python :: 3.6
Classifier: Programming Language :: Python :: 3.7
Classifier: Programming Language :: Python :: 3.8
Classifier: Programming Language :: Python :: 3.9
Classifier: Programming Language :: Python :: 3.10
Classifier: Programming Language :: Python :: 3.11
Classifier: Topic :: Scientific/Engineering
Classifier: Topic :: Software Development
License-File: LICENSE
Requires-Dist: argcomplete>=1.12.3
Requires-Dist: argparse>=1.1
Requires-Dist: colour_demosaicing>=0.1.5
Requires-Dist: geographiclib>=1.50
Requires-Dist: imageio>=2.6.1
Requires-Dist: joblib>=0.14.1
Requires-Dist: matplotlib>=3.2.1
Requires-Dist: numba>=0.56.4
Requires-Dist: numpy>=1.23.0
Requires-Dist: opencv-python-headless>=4.1.2
Requires-Dist: pandas>=0.25.3
Requires-Dist: pillow>=7.2.0
Requires-Dist: plotly>=4.7.1
Requires-Dist: plyfile>=0.7.2
Requires-Dist: prettytable>=3.5.0
Requires-Dist: psutil>=5.8.0
Requires-Dist: pynmea2>=1.15.0
Requires-Dist: pytz>=2019.3
Requires-Dist: PyYAML>=3.12
Requires-Dist: scikit_image>=0.17
Requires-Dist: scipy>=1.4.1
Requires-Dist: tqdm>=4.64.0
Requires-Dist: wheel>=0.30.0
Dynamic: author
Dynamic: author-email
Dynamic: classifier
Dynamic: description
Dynamic: description-content-type
Dynamic: home-page
Dynamic: license
Dynamic: license-file
Dynamic: requires-dist
Dynamic: summary
